cuesdk/__init__.py
cuesdk/api.py
cuesdk/enums.py
cuesdk/helpers.py
cuesdk/structs.py
cuesdk/version.py
cuesdk/bin/iCUESDK.x64_2019.dll
cuesdk/bin/libiCUESDK.dylib
cuesdk/native/__init__.py
cuesdk/native/capi.py
cuesdk/native/structs.py
cuesdk-4.0.84.dist-info/LICENSE
cuesdk-4.0.84.dist-info/METADATA
cuesdk-4.0.84.dist-info/WHEEL
cuesdk-4.0.84.dist-info/top_level.txt
cuesdk-4.0.84.dist-info/RECORD
