Metadata-Version: 2.1
Name: cuesdk
Version: 4.0.84
Summary: Ctypes-based CUE SDK binding for Python
Home-page: https://github.com/CorsairOfficial/cue-sdk-python
Author: Corsair Memory, Inc.
License: MIT
Classifier: Development Status :: 5 - Production/Stable
Classifier: Intended Audience :: Developers
Classifier: Intended Audience :: End Users/Desktop
Classifier: License :: OSI Approved :: MIT License
Classifier: Operating System :: MacOS
Classifier: Operating System :: MacOS :: MacOS X
Classifier: Operating System :: Microsoft :: Windows
Classifier: Programming Language :: Python :: 3.9
Classifier: Programming Language :: Python :: 3.10
Classifier: Programming Language :: Python :: Implementation :: CPython
Classifier: Topic :: Games/Entertainment
Classifier: Topic :: System :: Hardware
Requires-Python: >=3.9
License-File: LICENSE
